<?xml version = '1.0' encoding = 'UTF-8'?>
<EmsSAPArMessage><Header><MessageId>2HGJ0001-25-26</MessageId><Scope>Accounting</Scope><DateTimeStamp>20250721 13:09</DateTimeStamp><DataSource>EMS</DataSource></Header><Invoice><InvoiceHeader><BusinessActivity>RFBU</BusinessActivity><DocumentType>X2</DocumentType><DocumentDate>20240229</DocumentDate><PostingDate>20250721</PostingDate><AccountingPeriodMonth>07</AccountingPeriodMonth><AccountingPeriodYear>2025</AccountingPeriodYear><InternalLegalEntity/><DocHeaderText>Gujarat/SEIPL-GJ - BU</DocHeaderText><RefNum>2HGJ0001/25-26</RefNum><EmsRefNum>2HGJ0001/25-26</EmsRefNum><Currency>USD</Currency><LocalCurrency/><ExchangeRate/><CalculateTax/><TranslationDate/><TradingPartnerBusinessArea/><AddressLine>SIETCO-1</AddressLine><AddressLine>THE METROPOLIS TOWER 1 9 NORTH BUONA VISTA DRIVE 07 TO 01</AddressLine><AddressLine>SINGAPORE</AddressLine><AddressLine>SINGAPORE</AddressLine><AddressLine>138588</AddressLine><AddressLine/><AddressLine/><AddressLine/><UserName>BIPSUP</UserName></InvoiceHeader><InvoiceDetail><CustomerId>G1897</CustomerId><LineSeqNo>1</LineSeqNo><PostingKey>01</PostingKey><TransactionType/><CurrencyAmount>84340.00</CurrencyAmount><LocalCurrencyAmount/><TaxCode/><BusinessArea/><ItemText>2HGJ0001/25-26</ItemText><Volume>4000.00</Volume><VolumeUnit>MMB</VolumeUnit><ReferenceKey1>2V230010-1</ReferenceKey1><ReferenceKey2>BIPSUP</ReferenceKey2><ProductionPeriod>202310</ProductionPeriod><AssignmentNumber>2HGJ0001/25-26</AssignmentNumber><PaymentTerms>ZB00</PaymentTerms><PaymentDueDate>20240301</PaymentDueDate><Material>000000000001168001</Material></InvoiceDetail><InvoiceDetail><CustomerId>G1897</CustomerId><LineSeqNo>2</LineSeqNo><PostingKey>50</PostingKey><Account>0006841000</Account><TransactionType/><CurrencyAmount>-44436.00</CurrencyAmount><LocalCurrencyAmount/><TaxCode/><BusinessArea/><ItemText>Swaps IG Oct 2023 (30-8 (ITWFDV231003))</ItemText><Volume>4000.00</Volume><VolumeUnit>MMB</VolumeUnit><ReferenceKey1>2V230008-1</ReferenceKey1><ReferenceKey2>BIPSUP</ReferenceKey2><ProductionPeriod>202310</ProductionPeriod><AssignmentNumber>2HGJ0001/25-26</AssignmentNumber><PaymentTerms>ZB00</PaymentTerms><PaymentDueDate>20240301</PaymentDueDate><Material>000000000001168001</Material></InvoiceDetail><InvoiceDetail><CustomerId>G1897</CustomerId><LineSeqNo>3</LineSeqNo><PostingKey>50</PostingKey><Account>0006841000</Account><TransactionType/><CurrencyAmount>-29132.00</CurrencyAmount><LocalCurrencyAmount/><TaxCode/><BusinessArea/><ItemText>Swaps IG Oct 2023 (30-9)</ItemText><Volume>4000.00</Volume><VolumeUnit>MMB</VolumeUnit><ReferenceKey1>2V230009-1</ReferenceKey1><ReferenceKey2>BIPSUP</ReferenceKey2><ProductionPeriod>202310</ProductionPeriod><AssignmentNumber>2HGJ0001/25-26</AssignmentNumber><PaymentTerms>ZB00</PaymentTerms><PaymentDueDate>20240301</PaymentDueDate><Material>000000000001168001</Material></InvoiceDetail><InvoiceDetail><CustomerId>G1897</CustomerId><LineSeqNo>4</LineSeqNo><PostingKey>50</PostingKey><Account>0006841000</Account><TransactionType/><CurrencyAmount>-10772.00</CurrencyAmount><LocalCurrencyAmount/><TaxCode/><BusinessArea/><ItemText>Swaps IG Oct 2023 (30-10)</ItemText><Volume>4000.00</Volume><VolumeUnit>MMB</VolumeUnit><ReferenceKey1>2V230010-1</ReferenceKey1><ReferenceKey2>BIPSUP</ReferenceKey2><ProductionPeriod>202310</ProductionPeriod><AssignmentNumber>2HGJ0001/25-26</AssignmentNumber><PaymentTerms>ZB00</PaymentTerms><PaymentDueDate>20240301</PaymentDueDate><Material>000000000001168001</Material></InvoiceDetail></Invoice></EmsSAPArMessage>